ProteinPreprocessing/Alignment.py
ProteinPreprocessing/Preparation.py
ProteinPreprocessing/__init__.py
ProteinPreprocessing/Example/__init__.py
ProteinPreprocessing/Example/example.py
SiMBols/SiMBols.py
SiMBols/__init__.py
SiMBols/ProteinPreprocessing/Alignment.py
SiMBols/ProteinPreprocessing/Preparation.py
SiMBols/ProteinPreprocessing/__init__.py
SiMBols/ProteinPreprocessing/Example/__init__.py
SiMBols/ProteinPreprocessing/Example/example.py
simbols-1.0.4.dist-info/LICENSE
simbols-1.0.4.dist-info/METADATA
simbols-1.0.4.dist-info/WHEEL
simbols-1.0.4.dist-info/top_level.txt
simbols-1.0.4.dist-info/RECORD
